envoy_extproc_sdk/__init__.py
envoy_extproc_sdk/__main__.py
envoy_extproc_sdk/extproc.py
envoy_extproc_sdk/health.py
envoy_extproc_sdk/server.py
envoy_extproc_sdk/settings.py
envoy_extproc_sdk/testing/__init__.py
envoy_extproc_sdk/testing/extproc.py
envoy_extproc_sdk/testing/http.py
envoy_extproc_sdk/util/__init__.py
envoy_extproc_sdk/util/envoy.py
envoy_extproc_sdk/util/timer.py
envoy_extproc_sdk-0.1.1.dist-info/WHEEL
envoy_extproc_sdk-0.1.1.dist-info/METADATA
envoy_extproc_sdk-0.1.1.dist-info/RECORD
