Metadata-Version: 2.1
Name: envoy-extproc-sdk
Version: 0.1.1
Summary: A python SDK for envoy External Processors
Home-page: https://github.com/wrossmorrow/envoy-extproc-sdk
License: Apache-2.0
Author: W. Ross Morrow
Author-email: morrowwr@gmail.com
Requires-Python: >=3.9,<4.0
Classifier: License :: OSI Approved :: Apache Software License
Classifier: Programming Language :: Python :: 3
Classifier: Programming Language :: Python :: 3.10
Classifier: Programming Language :: Python :: 3.9
Requires-Dist: datadog (>=0.44.0,<0.45.0)
Requires-Dist: ddtrace
Requires-Dist: grpcio (>=1.46.1,<2.0.0)
Requires-Dist: grpclib (>=0.4.2,<0.5.0)
Requires-Dist: protoc-gen-validate (>=0.4.2,<0.5.0)
Project-URL: Repository, https://github.com/wrossmorrow/envoy-extproc-sdk
